df2mysql/__init__.py
df2mysql/database.py
df2mysql-0.0.3.dist-info/LICENSE
df2mysql-0.0.3.dist-info/METADATA
df2mysql-0.0.3.dist-info/WHEEL
df2mysql-0.0.3.dist-info/top_level.txt
df2mysql-0.0.3.dist-info/RECORD
