Metadata-Version: 2.1
Name: df2mysql
Version: 0.0.3
Summary: 提供了一组方法，用于与 Microsoft SQL Server 数据库进行交互。允许执行各种操作，如连接到 SQL Server、创建和删除数据库、创建和删除表、添加和删除列、插入和检索数据等。
Home-page: https://github.com/ng-fukgin/df2mysql
Author: wfj
Author-email: wfj <wfj.0000@gmail.com>
License: MIT
Project-URL: homepage, https://github.com/ng-fukgin/df2mysql
Project-URL: repository, https://github.com/ng-fukgin/df2mysql
Project-URL: documentation, https://github.com/ng-fukgin/df2mysql/wiki
Project-URL: bugtracker, https://github.com/ng-fukgin/df2mysql/issues
Keywords: df2mysql,Microsoft SQL Server,数据库交互,数据库连接,数据库操作,数据库管理
Platform: any
Classifier: Development Status :: 3 - Alpha
Classifier: Intended Audience :: Developers
Classifier: License :: OSI Approved :: MIT License
Classifier: Programming Language :: Python
Classifier: Programming Language :: Python :: 3
Classifier: Programming Language :: Python :: 3.6
Classifier: Programming Language :: Python :: 3.7
Classifier: Programming Language :: Python :: 3.8
Classifier: Programming Language :: Python :: 3.9
Classifier: Operating System :: OS Independent
Requires-Python: >=3.7
License-File: LICENSE
Requires-Dist: pymssql
Requires-Dist: pandas
